<?xml version="1.0" encoding="utf-8"?>
<EntityRelationships xmlns:xsi="http://www.w3.org/2001/XMLSchema-instance">
  <EntityRelationship Name="business_unit_devops_entitya" />
  <EntityRelationship Name="business_unit_devops_entityb" />
  <EntityRelationship Name="lk_devops_entitya_createdby" />
  <EntityRelationship Name="lk_devops_entitya_modifiedby" />
  <EntityRelationship Name="lk_devops_entityb_createdby" />
  <EntityRelationship Name="lk_devops_entityb_modifiedby" />
  <EntityRelationship Name="owner_devops_entitya" />
  <EntityRelationship Name="owner_devops_entityb" />
  <EntityRelationship Name="team_devops_entitya" />
  <EntityRelationship Name="team_devops_entityb" />
  <EntityRelationship Name="user_devops_entitya" />
  <EntityRelationship Name="user_devops_entityb" />
</EntityRelationships>